{
  "dqpfyy_5403": [
    {
      "pffmtm_4757": "//game.gtimg.cn/images/yxzj/zlkdatasys/images/image/20220413/16498394925925.jpg",
      "pffmtm_8153": "//game.gtimg.cn/images/yxzj/zlkdatasys/images/image/20220413/16498394948606.jpg",
      "yylbzt_9132": [
        {
          "yywbzt_1517": "真的，会有人选择阿宓吗？",
          "yywjzt_5304": "//game.gtimg.cn/images/yxzj/zlkdatasys/audios/audio/20220412/16497738404586.wav",
          "ssjqmc_1356": "",
          "yygn_8632": "大厅语音1"
        },
        {
          "yywbzt_1517": "随波逐流的痛苦，你们不懂。",
          "yywjzt_5304": "//game.gtimg.cn/images/yxzj/zlkdatasys/audios/audio/20220412/16497738656295.wav",
          "ssjqmc_1356": "",
          "yygn_8632": "大厅语音2"
        },
        {
          "yywbzt_1517": "人家抒发哀伤时，不要随便破坏氛围好吗？",
          "yywjzt_5304": "//game.gtimg.cn/images/yxzj/zlkdatasys/audios/audio/20220412/16497738731930.wav",
          "ssjqmc_1356": "",
          "yygn_8632": "大厅语音3"
        },
        {
          "yywbzt_1517": "果然，先爱上的那个人，是输家。",
          "yywjzt_5304": "//game.gtimg.cn/images/yxzj/zlkdatasys/audios/audio/20220412/16497738954851.wav",
          "ssjqmc_1356": "",
          "yygn_8632": "移动语音1"
        },
        {
          "yywbzt_1517": "明明说好了，要永远在一起……",
          "yywjzt_5304": "//game.gtimg.cn/images/yxzj/zlkdatasys/audios/audio/20220412/16497739332385.wav",
          "ssjqmc_1356": "",
          "yygn_8632": "移动语音2"
        },
        {
          "yywbzt_1517": "别靠近我！阿宓，不想带来不幸……",
          "yywjzt_5304": "//game.gtimg.cn/images/yxzj/zlkdatasys/audios/audio/20220412/16497739468146.wav",
          "ssjqmc_1356": "",
          "yygn_8632": "移动语音3"
        },
        {
          "yywbzt_1517": "沦陷在爱情的泡影中。",
          "yywjzt_5304": "//game.gtimg.cn/images/yxzj/zlkdatasys/audios/audio/20220412/16497739662992.wav",
          "ssjqmc_1356": "",
          "yygn_8632": "移动语音4"
        },
        {
          "yywbzt_1517": "若轻风之蔽月，若流风之回雪。（选自曹植《洛神赋》）",
          "yywjzt_5304": "//game.gtimg.cn/images/yxzj/zlkdatasys/audios/audio/20220412/16497739781946.wav",
          "ssjqmc_1356": "",
          "yygn_8632": "移动语音5"
        },
        {
          "yywbzt_1517": "悲伤...逆流成河...",
          "yywjzt_5304": "//game.gtimg.cn/images/yxzj/zlkdatasys/audios/audio/20220412/16497739994008.wav",
          "ssjqmc_1356": "",
          "yygn_8632": "技能语音3"
        },
        {
          "yywbzt_1517": "女人，是水做的。",
          "yywjzt_5304": "//game.gtimg.cn/images/yxzj/zlkdatasys/audios/audio/20220412/16497740132743.wav",
          "ssjqmc_1356": "",
          "yygn_8632": "技能语音3"
        },
        {
          "yywbzt_1517": "波涛汹涌",
          "yywjzt_5304": "//game.gtimg.cn/images/yxzj/zlkdatasys/audios/audio/20220412/16497740241795.wav",
          "ssjqmc_1356": "",
          "yygn_8632": "技能语音3"
        },
        {
          "yywbzt_1517": "绝望吗？",
          "yywjzt_5304": "//game.gtimg.cn/images/yxzj/zlkdatasys/audios/audio/20220412/16497740457951.wav",
          "ssjqmc_1356": "",
          "yygn_8632": "击杀语音"
        },
        {
          "yywbzt_1517": "原来是只旱鸭子……",
          "yywjzt_5304": "//game.gtimg.cn/images/yxzj/zlkdatasys/audios/audio/20220412/16497740556071.wav",
          "ssjqmc_1356": "",
          "yygn_8632": "挑衅"
        }
      ],
      "pfmczt_7754": "洛神降临",
      "pffmtz_2425": "//game.gtimg.cn/images/yxzj/zlkdatasys/images/image/20220413/16498394966283.jpg",
      "pffmic_4237": "//game.gtimg.cn/images/yxzj/zlkdatasys/images/image/20220413/16498394998084.jpg"
    },
    {
      "pffmtm_4757": "//game.gtimg.cn/images/yxzj/zlkdatasys/images/image/20220413/16498465914413.jpg",
      "pffmtm_8153": "//game.gtimg.cn/images/yxzj/zlkdatasys/images/image/20220415/16499956835911.jpg",
      "yylbzt_9132": [
        {
          "yywbzt_1517": "不到园林，怎知春色如许？",
          "yywjzt_5304": "//game.gtimg.cn/images/yxzj/zlkdatasys/audios/audio/20220412/16497742337085.wav",
          "ssjqmc_1356": "",
          "yygn_8632": "大厅语音1"
        },
        {
          "yywbzt_1517": "晓来望断梅关，宿妆残",
          "yywjzt_5304": "//game.gtimg.cn/images/yxzj/zlkdatasys/audios/audio/20220412/16497742471147.wav",
          "ssjqmc_1356": "",
          "yygn_8632": "大厅语音2"
        },
        {
          "yywbzt_1517": "春哪春，得和你两留连，春去如何遣？",
          "yywjzt_5304": "//game.gtimg.cn/images/yxzj/zlkdatasys/audios/audio/20220412/16497742978750.mp3",
          "ssjqmc_1356": "",
          "yygn_8632": "大厅语音3"
        },
        {
          "yywbzt_1517": "牡丹亭畔春梦残",
          "yywjzt_5304": "//game.gtimg.cn/images/yxzj/zlkdatasys/audios/audio/20220412/16497743894616.wav",
          "ssjqmc_1356": "",
          "yygn_8632": "移动语音3"
        },
        {
          "yywbzt_1517": "徘徊恨叠怯衣单（选自汤显祖《阮郎归·不经人事意相关》）",
          "yywjzt_5304": "//game.gtimg.cn/images/yxzj/zlkdatasys/audios/audio/20220412/16497744024371.wav",
          "ssjqmc_1356": "",
          "yygn_8632": "移动语音4"
        },
        {
          "yywbzt_1517": "春梦暗随三月景",
          "yywjzt_5304": "//game.gtimg.cn/images/yxzj/zlkdatasys/audios/audio/20220412/16497744149060.wav",
          "ssjqmc_1356": "",
          "yygn_8632": "移动语音5"
        },
        {
          "yywbzt_1517": "晓寒瘦却一分花",
          "yywjzt_5304": "//game.gtimg.cn/images/yxzj/zlkdatasys/audios/audio/20220412/16497744286345.wav",
          "ssjqmc_1356": "",
          "yygn_8632": "移动语音6"
        },
        {
          "yywbzt_1517": "昨日梦里，那书生将柳枝来赠奴，要奴题詠",
          "yywjzt_5304": "//game.gtimg.cn/images/yxzj/zlkdatasys/audios/audio/20220412/16497744456526.wav",
          "ssjqmc_1356": "",
          "yygn_8632": "移动语音7"
        },
        {
          "yywbzt_1517": "他年的傍蟾宫客",
          "yywjzt_5304": "//game.gtimg.cn/images/yxzj/zlkdatasys/audios/audio/20220412/16497744595605.wav",
          "ssjqmc_1356": "",
          "yygn_8632": "移动语音8"
        },
        {
          "yywbzt_1517": "不在梅边在柳边",
          "yywjzt_5304": "//game.gtimg.cn/images/yxzj/zlkdatasys/audios/audio/20220412/16497744756109.wav",
          "ssjqmc_1356": "",
          "yygn_8632": "移动语音9"
        },
        {
          "yywbzt_1517": "趁此悄地无人，正好寻梦也。",
          "yywjzt_5304": "//game.gtimg.cn/images/yxzj/zlkdatasys/audios/audio/20220412/16497745157879.mp3",
          "ssjqmc_1356": "",
          "yygn_8632": "移动语音1"
        },
        {
          "yywbzt_1517": "漫道柔情著意关",
          "yywjzt_5304": "//game.gtimg.cn/images/yxzj/zlkdatasys/audios/audio/20220412/16497745647520.wav",
          "ssjqmc_1356": "",
          "yygn_8632": "移动语音2"
        },
        {
          "yywbzt_1517": "得葬于此，幸矣。",
          "yywjzt_5304": "//game.gtimg.cn/images/yxzj/zlkdatasys/audios/audio/20220412/16497746098683.wav",
          "ssjqmc_1356": "",
          "yygn_8632": "死亡语音"
        },
        {
          "yywbzt_1517": "池馆苍苔一片青",
          "yywjzt_5304": "//game.gtimg.cn/images/yxzj/zlkdatasys/audios/audio/20220412/16497746396499.wav",
          "ssjqmc_1356": "",
          "yygn_8632": "技能语音3"
        },
        {
          "yywbzt_1517": "哪里去",
          "yywjzt_5304": "//game.gtimg.cn/images/yxzj/zlkdatasys/audios/audio/20220412/16497746516265.wav",
          "ssjqmc_1356": "",
          "yygn_8632": "技能语音3"
        },
        {
          "yywbzt_1517": "只为痴情慕色，一梦而亡",
          "yywjzt_5304": "//game.gtimg.cn/images/yxzj/zlkdatasys/audios/audio/20220412/16497746659241.wav",
          "ssjqmc_1356": "",
          "yygn_8632": "击杀语音"
        },
        {
          "yywbzt_1517": "那牡丹亭，芍药栏，怎生这般凄凉冷落",
          "yywjzt_5304": "//game.gtimg.cn/images/yxzj/zlkdatasys/audios/audio/20220412/16497746773871.wav",
          "ssjqmc_1356": "",
          "yygn_8632": "挑衅"
        }
      ],
      "pfmczt_7754": "游园惊梦",
      "pffmtz_2425": "//game.gtimg.cn/images/yxzj/zlkdatasys/images/image/20220415/16499956895888.jpg",
      "pffmic_4237": "//game.gtimg.cn/images/yxzj/zlkdatasys/images/image/20220413/16498466185767.jpg"
    },
    {
      "pffmtm_4757": "//game.gtimg.cn/images/yxzj/zlkdatasys/images/image/20220413/16498466434473.jpg",
      "pffmtm_8153": "//game.gtimg.cn/images/yxzj/zlkdatasys/images/image/20220413/16498466569873.jpg",
      "yylbzt_9132": [
        {
          "yywbzt_1517": "撼天地，镇乾坤",
          "yywjzt_5304": "//game.gtimg.cn/images/yxzj/zlkdatasys/audios/audio/20220414/16499306195871.mp3",
          "ssjqmc_1356": "",
          "yygn_8632": "大厅语音1"
        },
        {
          "yywbzt_1517": "恒山如行，御风绝顶。（选自魏源《衡岳吟》；李公昴 《满江红（江西持宪节、登高作）》）",
          "yywjzt_5304": "//game.gtimg.cn/images/yxzj/zlkdatasys/audios/audio/20220414/16499306348727.mp3",
          "ssjqmc_1356": "",
          "yygn_8632": "大厅语音2"
        },
        {
          "yywbzt_1517": "星辰入怀！",
          "yywjzt_5304": "//game.gtimg.cn/images/yxzj/zlkdatasys/audios/audio/20220414/16499306465371.mp3",
          "ssjqmc_1356": "",
          "yygn_8632": "大厅语音3"
        },
        {
          "yywbzt_1517": "生如尘露，亦能折射朝阳之晖",
          "yywjzt_5304": "//game.gtimg.cn/images/yxzj/zlkdatasys/audios/audio/20220412/16497752289424.wav",
          "ssjqmc_1356": "",
          "yygn_8632": "移动语音1"
        },
        {
          "yywbzt_1517": "其刚不可折，其柔不可卷",
          "yywjzt_5304": "//game.gtimg.cn/images/yxzj/zlkdatasys/audios/audio/20220412/16497752422893.wav",
          "ssjqmc_1356": "",
          "yygn_8632": "移动语音2"
        },
        {
          "yywbzt_1517": "一愿世间昌平，二愿海晏河清",
          "yywjzt_5304": "//game.gtimg.cn/images/yxzj/zlkdatasys/audios/audio/20220412/16497752534742.wav",
          "ssjqmc_1356": "",
          "yygn_8632": "移动语音3"
        },
        {
          "yywbzt_1517": "此歌此曲，为恐惧和迷茫而奏",
          "yywjzt_5304": "//game.gtimg.cn/images/yxzj/zlkdatasys/audios/audio/20220412/16497752644827.wav",
          "ssjqmc_1356": "",
          "yygn_8632": "移动语音4"
        },
        {
          "yywbzt_1517": "斯人韶华易逝，苍翠万古常新",
          "yywjzt_5304": "//game.gtimg.cn/images/yxzj/zlkdatasys/audios/audio/20220412/16497752756860.wav",
          "ssjqmc_1356": "",
          "yygn_8632": "移动语音5"
        },
        {
          "yywbzt_1517": "死得其所，无怨无悔",
          "yywjzt_5304": "//game.gtimg.cn/images/yxzj/zlkdatasys/audios/audio/20220412/16497752977412.wav",
          "ssjqmc_1356": "",
          "yygn_8632": "死亡语音"
        },
        {
          "yywbzt_1517": "恒宗极天！",
          "yywjzt_5304": "//game.gtimg.cn/images/yxzj/zlkdatasys/audios/audio/20220412/16497753198535.wav",
          "ssjqmc_1356": "",
          "yygn_8632": "技能语音3-1"
        },
        {
          "yywbzt_1517": "灵境清幽，何不停留~",
          "yywjzt_5304": "//game.gtimg.cn/images/yxzj/zlkdatasys/audios/audio/20220412/16497753305095.wav",
          "ssjqmc_1356": "",
          "yygn_8632": "技能语音3-2"
        },
        {
          "yywbzt_1517": "还人间一片净土！",
          "yywjzt_5304": "//game.gtimg.cn/images/yxzj/zlkdatasys/audios/audio/20220412/16497753833794.wav",
          "ssjqmc_1356": "",
          "yygn_8632": "击杀语音"
        },
        {
          "yywbzt_1517": "小女子尚在阵前，大丈夫却要回城？",
          "yywjzt_5304": "//game.gtimg.cn/images/yxzj/zlkdatasys/audios/audio/20220412/16497754176319.wav",
          "ssjqmc_1356": "",
          "yygn_8632": "挑衅"
        },
        {
          "yywbzt_1517": "长歌吟星河~",
          "yywjzt_5304": "//game.gtimg.cn/images/yxzj/zlkdatasys/audios/audio/20220412/16497754299936.wav",
          "ssjqmc_1356": "",
          "yygn_8632": "个性动作"
        },
        {
          "yywbzt_1517": "那天，人间会再次想起永安之箭",
          "yywjzt_5304": "//game.gtimg.cn/images/yxzj/zlkdatasys/audios/audio/20220412/16497754391195.wav",
          "ssjqmc_1356": "",
          "yygn_8632": "相遇伽罗"
        },
        {
          "yywbzt_1517": "琴瑟已备，静候诸君凯旋",
          "yywjzt_5304": "//game.gtimg.cn/images/yxzj/zlkdatasys/audios/audio/20220412/16497754505002.wav",
          "ssjqmc_1356": "",
          "yygn_8632": "相遇韩信"
        },
        {
          "yywbzt_1517": "你的背影不倒，我们的信念不灭",
          "yywjzt_5304": "//game.gtimg.cn/images/yxzj/zlkdatasys/audios/audio/20220412/16497754639357.wav",
          "ssjqmc_1356": "",
          "yygn_8632": "相遇典韦"
        },
        {
          "yywbzt_1517": "想不到，你的歌喉也很美妙",
          "yywjzt_5304": "//game.gtimg.cn/images/yxzj/zlkdatasys/audios/audio/20220428/16511307772140.mp3",
          "ssjqmc_1356": "",
          "yygn_8632": "相遇庄周"
        }
      ],
      "pfmczt_7754": "幽恒",
      "pffmtz_2425": "//game.gtimg.cn/images/yxzj/zlkdatasys/images/image/20220413/16498466638355.jpg",
      "pffmic_4237": "//game.gtimg.cn/images/yxzj/zlkdatasys/images/image/20220413/16498466686020.jpg"
    },
    {
      "pffmtm_4757": "//game.gtimg.cn/images/yxzj/zlkdatasys/images/image/20220413/16498467699478.jpg",
      "pffmtm_8153": "//game.gtimg.cn/images/yxzj/zlkdatasys/images/image/20220413/16498467726057.jpg",
      "yylbzt_9132": [
        {
          "yywbzt_1517": "这颗心，曾因冰封而不朽",
          "yywjzt_5304": "//game.gtimg.cn/images/yxzj/zlkdatasys/audios/audio/20220414/16499307442535.mp3",
          "ssjqmc_1356": "",
          "yygn_8632": "大厅语音1"
        },
        {
          "yywbzt_1517": "最后一支舞，献给名为冬日的告别",
          "yywjzt_5304": "//game.gtimg.cn/images/yxzj/zlkdatasys/audios/audio/20220414/16499307566948.mp3",
          "ssjqmc_1356": "",
          "yygn_8632": "大厅语音2"
        },
        {
          "yywbzt_1517": "要再次触碰那朵被冻结的玫瑰吗？",
          "yywjzt_5304": "//game.gtimg.cn/images/yxzj/zlkdatasys/audios/audio/20220414/16499307678152.mp3",
          "ssjqmc_1356": "",
          "yygn_8632": "大厅语音3"
        },
        {
          "yywbzt_1517": "凡人生命短暂，却轻易许诺永恒",
          "yywjzt_5304": "//game.gtimg.cn/images/yxzj/zlkdatasys/audios/audio/20220413/16498427267602.wav",
          "ssjqmc_1356": "",
          "yygn_8632": "移动语音1"
        },
        {
          "yywbzt_1517": "我将赐还你们爱的能力，痛苦是它的附赠品",
          "yywjzt_5304": "//game.gtimg.cn/images/yxzj/zlkdatasys/audios/audio/20220413/16498427384030.wav",
          "ssjqmc_1356": "",
          "yygn_8632": "移动语音2"
        },
        {
          "yywbzt_1517": "万物瞬变，冰霜弥久",
          "yywjzt_5304": "//game.gtimg.cn/images/yxzj/zlkdatasys/audios/audio/20220413/16498427521122.wav",
          "ssjqmc_1356": "",
          "yygn_8632": "移动语音3"
        },
        {
          "yywbzt_1517": "在属于人间的童话中，神不会感到孤独",
          "yywjzt_5304": "//game.gtimg.cn/images/yxzj/zlkdatasys/audios/audio/20220413/16498427645548.wav",
          "ssjqmc_1356": "",
          "yygn_8632": "移动语音4"
        },
        {
          "yywbzt_1517": "来吧，陪我共舞此曲，直到寒夜尽头",
          "yywjzt_5304": "//game.gtimg.cn/images/yxzj/zlkdatasys/audios/audio/20220413/16498427789384.wav",
          "ssjqmc_1356": "",
          "yygn_8632": "移动语音5"
        },
        {
          "yywbzt_1517": "当誓言破灭……",
          "yywjzt_5304": "//game.gtimg.cn/images/yxzj/zlkdatasys/audios/audio/20220413/16498427951269.wav",
          "ssjqmc_1356": "",
          "yygn_8632": "死亡语音"
        },
        {
          "yywbzt_1517": "凛冬降临！",
          "yywjzt_5304": "//game.gtimg.cn/images/yxzj/zlkdatasys/audios/audio/20220413/16498428137328.wav",
          "ssjqmc_1356": "",
          "yygn_8632": "技能3-1"
        },
        {
          "yywbzt_1517": "去最寒冷的地方绽放！",
          "yywjzt_5304": "//game.gtimg.cn/images/yxzj/zlkdatasys/audios/audio/20220413/16498428271607.wav",
          "ssjqmc_1356": "",
          "yygn_8632": "技能3-2"
        },
        {
          "yywbzt_1517": "留在冰雪的国度！",
          "yywjzt_5304": "//game.gtimg.cn/images/yxzj/zlkdatasys/audios/audio/20220413/16498428416517.wav",
          "ssjqmc_1356": "",
          "yygn_8632": "技能3-3"
        },
        {
          "yywbzt_1517": "刺伤你的，正是你所追求的",
          "yywjzt_5304": "//game.gtimg.cn/images/yxzj/zlkdatasys/audios/audio/20220413/16498428564175.wav",
          "ssjqmc_1356": "",
          "yygn_8632": "挑衅"
        },
        {
          "yywbzt_1517": "赐你灵魂永生！",
          "yywjzt_5304": "//game.gtimg.cn/images/yxzj/zlkdatasys/audios/audio/20220413/16498428715056.wav",
          "ssjqmc_1356": "",
          "yygn_8632": "击杀"
        },
        {
          "yywbzt_1517": "记忆中的旋律，再度响起……",
          "yywjzt_5304": "//game.gtimg.cn/images/yxzj/zlkdatasys/audios/audio/20220413/16498428855040.wav",
          "ssjqmc_1356": "",
          "yygn_8632": "个性动作"
        },
        {
          "yywbzt_1517": "没有什么能融化爱，除了爱本身",
          "yywjzt_5304": "//game.gtimg.cn/images/yxzj/zlkdatasys/audios/audio/20220413/16498429001043.wav",
          "ssjqmc_1356": "",
          "yygn_8632": "相遇-干将莫邪冰霜恋舞曲"
        }
      ],
      "pfmczt_7754": "冰雪圆舞曲",
      "pffmtz_2425": "//game.gtimg.cn/images/yxzj/zlkdatasys/images/image/20220413/16498467753168.jpg",
      "pffmic_4237": "//game.gtimg.cn/images/yxzj/zlkdatasys/images/image/20220413/16498467789132.jpg"
    },
    {
      "pffmtm_4757": "//game.gtimg.cn/images/yxzj/zlkdatasys/images/image/20220413/16498468843434.jpg",
      "pffmtm_8153": "//game.gtimg.cn/images/yxzj/zlkdatasys/images/image/20220413/16498468888113.jpg",
      "yylbzt_9132": [
        {
          "yywbzt_1517": "离合聚散，因缘早定。",
          "yywjzt_5304": "//game.gtimg.cn/images/yxzj/zlkdatasys/audios/audio/20220414/16499306846616.mp3",
          "ssjqmc_1356": "",
          "yygn_8632": "大厅出现1"
        },
        {
          "yywbzt_1517": "我只想今生，不想来世。",
          "yywjzt_5304": "//game.gtimg.cn/images/yxzj/zlkdatasys/audios/audio/20220414/16499306953238.mp3",
          "ssjqmc_1356": "",
          "yygn_8632": "大厅出现2"
        },
        {
          "yywbzt_1517": "君且西去，春事依然。",
          "yywjzt_5304": "//game.gtimg.cn/images/yxzj/zlkdatasys/audios/audio/20220414/16499307081828.mp3",
          "ssjqmc_1356": "",
          "yygn_8632": "大厅出现3"
        },
        {
          "yywbzt_1517": "为什么天地间鸟啊，蝶啊，都是成双成对？",
          "yywjzt_5304": "//game.gtimg.cn/images/yxzj/zlkdatasys/audios/audio/20220413/16498179938012.wav",
          "ssjqmc_1356": "",
          "yygn_8632": "移动语音1"
        },
        {
          "yywbzt_1517": "为什么你甘愿守青灯，伴古佛，单宿单飞？",
          "yywjzt_5304": "//game.gtimg.cn/images/yxzj/zlkdatasys/audios/audio/20220413/16498180138486.wav",
          "ssjqmc_1356": "",
          "yygn_8632": "移动语音2"
        },
        {
          "yywbzt_1517": "你说四大皆空，却为何紧闭双眼。",
          "yywjzt_5304": "//game.gtimg.cn/images/yxzj/zlkdatasys/audios/audio/20220413/16498180385906.wav",
          "ssjqmc_1356": "",
          "yygn_8632": "移动语音3"
        },
        {
          "yywbzt_1517": "原来这世上，比之成双鸳侣，多得却是相思枉然。",
          "yywjzt_5304": "//game.gtimg.cn/images/yxzj/zlkdatasys/audios/audio/20220413/16498180554962.wav",
          "ssjqmc_1356": "",
          "yygn_8632": "移动语音4"
        },
        {
          "yywbzt_1517": "这烛光也知人情，欲照今日之喜。",
          "yywjzt_5304": "//game.gtimg.cn/images/yxzj/zlkdatasys/audios/audio/20220413/16498183695020.wav",
          "ssjqmc_1356": "",
          "yygn_8632": "移动语音5"
        },
        {
          "yywbzt_1517": "金屏生彩艳，玉镜展光明，也许是今日之喜兆。",
          "yywjzt_5304": "//game.gtimg.cn/images/yxzj/zlkdatasys/audios/audio/20220413/16498183927057.wav",
          "ssjqmc_1356": "",
          "yygn_8632": "移动语音6"
        },
        {
          "yywbzt_1517": "这御花园内春光明媚，何不留下？",
          "yywjzt_5304": "//game.gtimg.cn/images/yxzj/zlkdatasys/audios/audio/20220413/16498184116235.wav",
          "ssjqmc_1356": "",
          "yygn_8632": "移动语音7"
        },
        {
          "yywbzt_1517": "若你睁开眼睛看看我，我不相信你两眼空空。",
          "yywjzt_5304": "//game.gtimg.cn/images/yxzj/zlkdatasys/audios/audio/20220413/16498184276809.wav",
          "ssjqmc_1356": "",
          "yygn_8632": "移动语音8"
        },
        {
          "yywbzt_1517": "想我西梁女国，从未有过男子，今以一国之富，招他为王。",
          "yywjzt_5304": "//game.gtimg.cn/images/yxzj/zlkdatasys/audios/audio/20220413/16498184458997.wav",
          "ssjqmc_1356": "",
          "yygn_8632": "移动语音9"
        },
        {
          "yywbzt_1517": "不敢睁眼看我，还说什么四大皆空呢？",
          "yywjzt_5304": "//game.gtimg.cn/images/yxzj/zlkdatasys/audios/audio/20220413/16498184579344.wav",
          "ssjqmc_1356": "",
          "yygn_8632": "移动语音10"
        },
        {
          "yywbzt_1517": "轻看王权富贵，便休说戒律清规。",
          "yywjzt_5304": "//game.gtimg.cn/images/yxzj/zlkdatasys/audios/audio/20220413/16498184706758.wav",
          "ssjqmc_1356": "",
          "yygn_8632": "移动语音11"
        },
        {
          "yywbzt_1517": "原是今生无缘......",
          "yywjzt_5304": "//game.gtimg.cn/images/yxzj/zlkdatasys/audios/audio/20220413/16498184985124.wav",
          "ssjqmc_1356": "",
          "yygn_8632": "死亡语音"
        },
        {
          "yywbzt_1517": "放肆，你们退下！",
          "yywjzt_5304": "//game.gtimg.cn/images/yxzj/zlkdatasys/audios/audio/20220413/16498185359612.wav",
          "ssjqmc_1356": "",
          "yygn_8632": "击杀语音"
        },
        {
          "yywbzt_1517": "相见难，别亦难。",
          "yywjzt_5304": "//game.gtimg.cn/images/yxzj/zlkdatasys/audios/audio/20220413/16498185562894.wav",
          "ssjqmc_1356": "",
          "yygn_8632": "回城"
        },
        {
          "yywbzt_1517": "看来，你无缘消受这人间富贵。",
          "yywjzt_5304": "//game.gtimg.cn/images/yxzj/zlkdatasys/audios/audio/20220413/16498185746179.wav",
          "ssjqmc_1356": "",
          "yygn_8632": "挑衅"
        },
        {
          "yywbzt_1517": "此心何寄？",
          "yywjzt_5304": "//game.gtimg.cn/images/yxzj/zlkdatasys/audios/audio/20220413/16498186175070.wav",
          "ssjqmc_1356": "",
          "yygn_8632": "技能语音3_1"
        },
        {
          "yywbzt_1517": "各自珍重！",
          "yywjzt_5304": "//game.gtimg.cn/images/yxzj/zlkdatasys/audios/audio/20220413/16498186365691.wav",
          "ssjqmc_1356": "",
          "yygn_8632": "技能语音3_2"
        },
        {
          "yywbzt_1517": "天涯路远，空挂牵……",
          "yywjzt_5304": "//game.gtimg.cn/images/yxzj/zlkdatasys/audios/audio/20220413/16498186556327.wav",
          "ssjqmc_1356": "",
          "yygn_8632": "技能语音3_3"
        },
        {
          "yywbzt_1517": "此为我西梁女国护身之宝。",
          "yywjzt_5304": "//game.gtimg.cn/images/yxzj/zlkdatasys/audios/audio/20220413/16498186821476.wav",
          "ssjqmc_1356": "",
          "yygn_8632": "个性动作"
        },
        {
          "yywbzt_1517": "子母河的水，轻易可喝不得。",
          "yywjzt_5304": "//game.gtimg.cn/images/yxzj/zlkdatasys/audios/audio/20220413/16498187088982.wav",
          "ssjqmc_1356": "",
          "yygn_8632": "相遇八戒"
        },
        {
          "yywbzt_1517": "喜筵已吃，却又如何变卦？！",
          "yywjzt_5304": "//game.gtimg.cn/images/yxzj/zlkdatasys/audios/audio/20220413/16498187825258.wav",
          "ssjqmc_1356": "",
          "yygn_8632": "相遇悟空"
        }
      ],
      "pfmczt_7754": "女儿国国王",
      "pffmtz_2425": "//game.gtimg.cn/images/yxzj/zlkdatasys/images/image/20220413/16498468943352.jpg",
      "pffmic_4237": "//game.gtimg.cn/images/yxzj/zlkdatasys/images/image/20220413/16498468981089.jpg"
    },
    {
      "pffmtm_4757": "//game.gtimg.cn/images/yxzj/zlkdatasys/images/image/20231109/16995125286171.jpg",
      "pffmtm_8153": "//game.gtimg.cn/images/yxzj/zlkdatasys/images/image/20231109/16995125249788.jpg",
      "yylbzt_9132": [
        {
          "yywbzt_1517": "展翅越荒丘，此舞不为世人囚。",
          "yywjzt_5304": "//game.gtimg.cn/images/yxzj/zlkdatasys/audios/audio/20231110/16995998545563.mp3",
          "ssjqmc_1356": "",
          "yygn_8632": "大厅出现1"
        },
        {
          "yywbzt_1517": "荆棘萦足，事与愿违，以心化雀而飞。",
          "yywjzt_5304": "//game.gtimg.cn/images/yxzj/zlkdatasys/audios/audio/20231110/16995998862671.mp3",
          "ssjqmc_1356": "",
          "yygn_8632": "大厅出现2"
        },
        {
          "yywbzt_1517": "舞为悦己，不悦人。",
          "yywjzt_5304": "//game.gtimg.cn/images/yxzj/zlkdatasys/audios/audio/20231110/16995999248424.mp3",
          "ssjqmc_1356": "",
          "yygn_8632": "大厅出现3"
        },
        {
          "yywbzt_1517": "漫天光翎化余烬，原道是，嫁与爱情。",
          "yywjzt_5304": "//game.gtimg.cn/images/yxzj/zlkdatasys/audios/audio/20231108/16994317938053.mp3",
          "ssjqmc_1356": "",
          "yygn_8632": "移动喊话1"
        },
        {
          "yywbzt_1517": "步战战，语兢兢，却惹窥度与相轻。",
          "yywjzt_5304": "//game.gtimg.cn/images/yxzj/zlkdatasys/audios/audio/20231108/16994321697396.mp3",
          "ssjqmc_1356": "",
          "yygn_8632": "移动喊话2"
        },
        {
          "yywbzt_1517": "低头未必示好，曲意不得逢迎。",
          "yywjzt_5304": "//game.gtimg.cn/images/yxzj/zlkdatasys/audios/audio/20231108/16994322156025.mp3",
          "ssjqmc_1356": "",
          "yygn_8632": "移动喊话3"
        },
        {
          "yywbzt_1517": "片羽零落终失我，又怎消，他人看低？",
          "yywjzt_5304": "//game.gtimg.cn/images/yxzj/zlkdatasys/audios/audio/20231108/16994322466353.mp3",
          "ssjqmc_1356": "",
          "yygn_8632": "移动喊话4"
        },
        {
          "yywbzt_1517": "我有身姿曼妙，曾越苍穹云霄。",
          "yywjzt_5304": "//game.gtimg.cn/images/yxzj/zlkdatasys/audios/audio/20231108/16994322763389.mp3",
          "ssjqmc_1356": "",
          "yygn_8632": "移动喊话5"
        },
        {
          "yywbzt_1517": "步绽随心，罗裙乘风最肆意。",
          "yywjzt_5304": "//game.gtimg.cn/images/yxzj/zlkdatasys/audios/audio/20231108/16994324166603.mp3",
          "ssjqmc_1356": "",
          "yygn_8632": "移动喊话6"
        },
        {
          "yywbzt_1517": "欢情纵有千般好，我心匪草，不可折。",
          "yywjzt_5304": "//game.gtimg.cn/images/yxzj/zlkdatasys/audios/audio/20231108/16994325335799.mp3",
          "ssjqmc_1356": "",
          "yygn_8632": "移动喊话7"
        },
        {
          "yywbzt_1517": "沐光化雀，舞翩跹，便是传奇数百年。",
          "yywjzt_5304": "//game.gtimg.cn/images/yxzj/zlkdatasys/audios/audio/20231108/16994325601183.mp3",
          "ssjqmc_1356": "",
          "yygn_8632": "移动喊话8"
        },
        {
          "yywbzt_1517": "过不好自己的日子，偏指点他人生活。",
          "yywjzt_5304": "//game.gtimg.cn/images/yxzj/zlkdatasys/audios/audio/20231108/16994325979585.mp3",
          "ssjqmc_1356": "",
          "yygn_8632": "挑衅语音"
        },
        {
          "yywbzt_1517": "干卿何事！",
          "yywjzt_5304": "//game.gtimg.cn/images/yxzj/zlkdatasys/audios/audio/20231108/16994326267841.mp3",
          "ssjqmc_1356": "",
          "yygn_8632": "击杀语音"
        },
        {
          "yywbzt_1517": "纵使零落亦有光……",
          "yywjzt_5304": "//game.gtimg.cn/images/yxzj/zlkdatasys/audios/audio/20231108/16994326685534.mp3",
          "ssjqmc_1356": "",
          "yygn_8632": "死亡语音"
        },
        {
          "yywbzt_1517": "竹楼虫语，孔雀声声起。",
          "yywjzt_5304": "//game.gtimg.cn/images/yxzj/zlkdatasys/audios/audio/20231110/16996140092226.mp3",
          "ssjqmc_1356": "",
          "yygn_8632": "回城语音"
        },
        {
          "yywbzt_1517": "只需盛放，我自有光！",
          "yywjzt_5304": "//game.gtimg.cn/images/yxzj/zlkdatasys/audios/audio/20231108/16994327438618.mp3",
          "ssjqmc_1356": "",
          "yygn_8632": "MVP"
        },
        {
          "yywbzt_1517": "化雀新生！",
          "yywjzt_5304": "//game.gtimg.cn/images/yxzj/zlkdatasys/audios/audio/20231108/16994327907631.mp3",
          "ssjqmc_1356": "",
          "yygn_8632": "技能语音3_1"
        },
        {
          "yywbzt_1517": "光翎盛开！",
          "yywjzt_5304": "//game.gtimg.cn/images/yxzj/zlkdatasys/audios/audio/20231108/16994328377868.mp3",
          "ssjqmc_1356": "",
          "yygn_8632": "技能语音3_2"
        },
        {
          "yywbzt_1517": "孔雀于飞，一舞徘徊！",
          "yywjzt_5304": "//game.gtimg.cn/images/yxzj/zlkdatasys/audios/audio/20231108/16994328775337.mp3",
          "ssjqmc_1356": "",
          "yygn_8632": "技能语音3_3"
        },
        {
          "yywbzt_1517": "凭心以往，何必相思。",
          "yywjzt_5304": "//game.gtimg.cn/images/yxzj/zlkdatasys/audios/audio/20231108/16994329108417.mp3",
          "ssjqmc_1356": "",
          "yygn_8632": "个性动作"
        },
        {
          "yywbzt_1517": "星光照我路，一舞化辰星。",
          "yywjzt_5304": "//game.gtimg.cn/images/yxzj/zlkdatasys/audios/audio/20231108/16994329403969.mp3",
          "ssjqmc_1356": "",
          "yygn_8632": "相遇-西施（友）"
        }
      ],
      "pfmczt_7754": "至美·化雀舞",
      "pffmtz_2425": "//game.gtimg.cn/images/yxzj/zlkdatasys/images/image/20231109/16995125192784.jpg",
      "pffmic_4237": "//game.gtimg.cn/images/yxzj/zlkdatasys/images/image/20231110/16996048985269.jpg"
    },
    {
      "pffmtm_4757": "//game.gtimg.cn/images/yxzj/zlkdatasys/images/image/20250116/17369908404311.jpg",
      "pffmtm_8153": "//game.gtimg.cn/images/yxzj/zlkdatasys/images/image/20250116/17369908433134.jpg",
      "yylbzt_9132": [
        {
          "yygn_8632": "大厅喊话1/Appearance (Lobby) 1",
          "yywbzt_1517": "有个声音说，别隐藏，别畏惧，尽情做自己。",
          "yywjzt_5304": "//game.gtimg.cn/images/yxzj/zlkdatasys/audios/audio/20250115/17369368262841.mp3",
          "ssjqmc_1356": ""
        },
        {
          "yygn_8632": "大厅喊话2/Appearance (Lobby) 2",
          "yywbzt_1517": "冥冥中的呼唤，正是期待已久的回音。",
          "yywjzt_5304": "//game.gtimg.cn/images/yxzj/zlkdatasys/audios/audio/20250115/17369368503325.mp3",
          "ssjqmc_1356": ""
        },
        {
          "yygn_8632": "大厅喊话3/Appearance (Lobby) 3",
          "yywbzt_1517": "寒冰虽冷，其心澄澈。",
          "yywjzt_5304": "//game.gtimg.cn/images/yxzj/zlkdatasys/audios/audio/20250115/17369368911684.mp3",
          "ssjqmc_1356": ""
        },
        {
          "yygn_8632": "展示待机/Idle Emote",
          "yywbzt_1517": "随心而行，探访远方！",
          "yywjzt_5304": "//game.gtimg.cn/images/yxzj/zlkdatasys/audios/audio/20250115/17369343484717.mp3",
          "ssjqmc_1356": ""
        },
        {
          "yygn_8632": "移动喊话1/Movement Line 1",
          "yywbzt_1517": "渴望自由的灵魂，远隔时空亦能共鸣。",
          "yywjzt_5304": "//game.gtimg.cn/images/yxzj/zlkdatasys/audios/audio/20250115/17369343742212.mp3",
          "ssjqmc_1356": ""
        },
        {
          "yygn_8632": "移动喊话2/Movement Line 2",
          "yywbzt_1517": "有些东西任时光更迭也不会改变。",
          "yywjzt_5304": "//game.gtimg.cn/images/yxzj/zlkdatasys/audios/audio/20250115/17369343995438.mp3",
          "ssjqmc_1356": ""
        },
        {
          "yygn_8632": "移动喊话3/Movement Line 3",
          "yywbzt_1517": "北风与海洋交汇之处，有一条河流盈满回忆……",
          "yywjzt_5304": "//game.gtimg.cn/images/yxzj/zlkdatasys/audios/audio/20250115/17369344226870.mp3",
          "ssjqmc_1356": ""
        },
        {
          "yygn_8632": "移动喊话4/Movement Line 4",
          "yywbzt_1517": "看不清未来，就只管做眼前该做的事。",
          "yywjzt_5304": "//game.gtimg.cn/images/yxzj/zlkdatasys/audios/audio/20250115/17369344498661.mp3",
          "ssjqmc_1356": ""
        },
        {
          "yygn_8632": "移动喊话5/Movement Line 5",
          "yywbzt_1517": "迎着风暴向前吧，不必再随波逐流！",
          "yywjzt_5304": "//game.gtimg.cn/images/yxzj/zlkdatasys/audios/audio/20250115/17369344755174.mp3",
          "ssjqmc_1356": ""
        },
        {
          "yygn_8632": "移动喊话6/Movement Line 6",
          "yywbzt_1517": "你想堆个雪人吗？",
          "yywjzt_5304": "//game.gtimg.cn/images/yxzj/zlkdatasys/audios/audio/20250115/17369345362053.mp3",
          "ssjqmc_1356": ""
        },
        {
          "yygn_8632": "移动喊话7/Movement Line 7",
          "yywbzt_1517": "故事里，女王终会打破魔咒，解救所有人。",
          "yywjzt_5304": "//game.gtimg.cn/images/yxzj/zlkdatasys/audios/audio/20250115/17369345606760.mp3",
          "ssjqmc_1356": ""
        },
        {
          "yygn_8632": "移动喊话8/Movement Line 8",
          "yywbzt_1517": "水是有记忆的。",
          "yywjzt_5304": "//game.gtimg.cn/images/yxzj/zlkdatasys/audios/audio/20250115/17369345844587.mp3",
          "ssjqmc_1356": ""
        },
        {
          "yygn_8632": "移动喊话9/Movement Line 9",
          "yywbzt_1517": "有些人值得为之融化。",
          "yywjzt_5304": "//game.gtimg.cn/images/yxzj/zlkdatasys/audios/audio/20250115/17369346193973.mp3",
          "ssjqmc_1356": ""
        },
        {
          "yygn_8632": "移动喊话10/Movement Line 10",
          "yywbzt_1517": "阳光、火焰、爱，我们总是向往温暖的事物。",
          "yywjzt_5304": "//game.gtimg.cn/images/yxzj/zlkdatasys/audios/audio/20250115/17369346554733.mp3",
          "ssjqmc_1356": ""
        },
        {
          "yygn_8632": "插旗/Destroy Enemy Tower",
          "yywbzt_1517": "敞开大门，展现真容！",
          "yywjzt_5304": "//game.gtimg.cn/images/yxzj/zlkdatasys/audios/audio/20250115/17369346814713.mp3",
          "ssjqmc_1356": ""
        },
        {
          "yygn_8632": "IDLE",
          "yywbzt_1517": "阿嚏！你们好呀，小家伙们。",
          "yywjzt_5304": "//game.gtimg.cn/images/yxzj/zlkdatasys/audios/audio/20250115/17369347146156.mp3",
          "ssjqmc_1356": ""
        },
        {
          "yygn_8632": "复活/Respawn",
          "yywbzt_1517": "一切尽失时，万物终再临！",
          "yywjzt_5304": "//game.gtimg.cn/images/yxzj/zlkdatasys/audios/audio/20250115/17369347851181.mp3",
          "ssjqmc_1356": ""
        },
        {
          "yygn_8632": "出生/Spawn",
          "yywbzt_1517": "从此刻起，我只回应自己的期待。",
          "yywjzt_5304": "//game.gtimg.cn/images/yxzj/zlkdatasys/audios/audio/20250115/17369348287070.mp3",
          "ssjqmc_1356": ""
        },
        {
          "yygn_8632": "败方MVP/MVP (Defeat)",
          "yywbzt_1517": "寒冬漫长，但我们会让太阳照常升起。",
          "yywjzt_5304": "//game.gtimg.cn/images/yxzj/zlkdatasys/audios/audio/20250115/17369348551211.mp3",
          "ssjqmc_1356": ""
        },
        {
          "yygn_8632": "胜方MVP/MVP (Victory)",
          "yywbzt_1517": "迷雾已经驱散，前路清晰可见。",
          "yywjzt_5304": "//game.gtimg.cn/images/yxzj/zlkdatasys/audios/audio/20250115/17369348868906.mp3",
          "ssjqmc_1356": ""
        },
        {
          "yygn_8632": "死亡喊话/Being Defeated Line",
          "yywbzt_1517": "为了正确的选择……",
          "yywjzt_5304": "//game.gtimg.cn/images/yxzj/zlkdatasys/audios/audio/20250115/17369349245164.mp3",
          "ssjqmc_1356": ""
        },
        {
          "yygn_8632": "击杀喊话/Defeat Line",
          "yywbzt_1517": "沉溺者，终迷失。",
          "yywjzt_5304": "//game.gtimg.cn/images/yxzj/zlkdatasys/audios/audio/20250115/17369349848605.mp3",
          "ssjqmc_1356": ""
        },
        {
          "yygn_8632": "挑衅/Taunt",
          "yywbzt_1517": "魔法并不可怕，恐惧才是强敌。",
          "yywjzt_5304": "//game.gtimg.cn/images/yxzj/zlkdatasys/audios/audio/20250115/17369350127035.mp3",
          "ssjqmc_1356": ""
        },
        {
          "yygn_8632": "一技能语音/Skill 1",
          "yywbzt_1517": "你们该离开了！",
          "yywjzt_5304": "//game.gtimg.cn/images/yxzj/zlkdatasys/audios/audio/20250115/17369350406742.mp3",
          "ssjqmc_1356": ""
        },
        {
          "yygn_8632": "一技能语音/Skill 1",
          "yywbzt_1517": "直面恐惧！",
          "yywjzt_5304": "//game.gtimg.cn/images/yxzj/zlkdatasys/audios/audio/20250115/17369350752073.mp3",
          "ssjqmc_1356": ""
        },
        {
          "yygn_8632": "二技能语音/Skill 2",
          "yywbzt_1517": "即刻现身！",
          "yywjzt_5304": "//game.gtimg.cn/images/yxzj/zlkdatasys/audios/audio/20250115/17369351097978.mp3",
          "ssjqmc_1356": ""
        },
        {
          "yygn_8632": "二技能语音/Skill 2",
          "yywbzt_1517": "奇迹恒久",
          "yywjzt_5304": "//game.gtimg.cn/images/yxzj/zlkdatasys/audios/audio/20250115/17369351511423.mp3",
          "ssjqmc_1356": ""
        },
        {
          "yygn_8632": "二技能语音/Skill 2",
          "yywbzt_1517": "趁雪化之前",
          "yywjzt_5304": "//game.gtimg.cn/images/yxzj/zlkdatasys/audios/audio/20250115/17369351916048.mp3",
          "ssjqmc_1356": ""
        },
        {
          "yygn_8632": "三技能语音/Skill 3",
          "yywbzt_1517": "灵魂生而自由",
          "yywjzt_5304": "//game.gtimg.cn/images/yxzj/zlkdatasys/audios/audio/20250115/17369352225996.mp3",
          "ssjqmc_1356": ""
        },
        {
          "yygn_8632": "三技能语音/Skill 3",
          "yywbzt_1517": "世界与天风同在",
          "yywjzt_5304": "//game.gtimg.cn/images/yxzj/zlkdatasys/audios/audio/20250115/17369352544150.mp3",
          "ssjqmc_1356": ""
        },
        {
          "yygn_8632": "三技能语音/Skill 3",
          "yywbzt_1517": "冲破枷锁，迎接黎明！",
          "yywjzt_5304": "//game.gtimg.cn/images/yxzj/zlkdatasys/audios/audio/20250115/17369352847602.mp3",
          "ssjqmc_1356": ""
        },
        {
          "yygn_8632": "三技能语音/Skill 3",
          "yywbzt_1517": "记忆如新，美梦依旧~",
          "yywjzt_5304": "//game.gtimg.cn/images/yxzj/zlkdatasys/audios/audio/20250115/17369353316686.mp3",
          "ssjqmc_1356": ""
        },
        {
          "yygn_8632": "三技能语音/Skill 3",
          "yywbzt_1517": "铭记此刻，铭记爱~",
          "yywjzt_5304": "//game.gtimg.cn/images/yxzj/zlkdatasys/audios/audio/20250115/17369353809849.mp3",
          "ssjqmc_1356": ""
        },
        {
          "yygn_8632": "三技能语音/Skill 3",
          "yywbzt_1517": "时间也无法使之腐朽~",
          "yywjzt_5304": "//game.gtimg.cn/images/yxzj/zlkdatasys/audios/audio/20250115/17369354168282.mp3",
          "ssjqmc_1356": ""
        },
        {
          "yygn_8632": "个性动作/Featured Emote",
          "yywbzt_1517": "准备好了吗？",
          "yywjzt_5304": "//game.gtimg.cn/images/yxzj/zlkdatasys/audios/audio/20250115/17369354497995.mp3",
          "ssjqmc_1356": ""
        },
        {
          "yygn_8632": "相遇1/Lady Zhen meets Xi Shi 1",
          "yywbzt_1517": "在这场冬日的盛典里，所有人皆会活成想要的模样。",
          "yywjzt_5304": "//game.gtimg.cn/images/yxzj/zlkdatasys/audios/audio/20250115/17369354807707.mp3",
          "ssjqmc_1356": ""
        },
        {
          "yygn_8632": "相遇2/Lady Zhen meets Xi Shi 2",
          "yywbzt_1517": "冬天太冷了。",
          "yywjzt_5304": "//game.gtimg.cn/images/yxzj/zlkdatasys/audios/audio/20250115/17369355113089.mp3",
          "ssjqmc_1356": ""
        },
        {
          "yygn_8632": "相遇3/Lady Zhen meets Xi Shi 3",
          "yywbzt_1517": "当然，用爱",
          "yywjzt_5304": "//game.gtimg.cn/images/yxzj/zlkdatasys/audios/audio/20250115/17369355407562.mp3",
          "ssjqmc_1356": ""
        }
      ],
      "pfmczt_7754": "雪境奇遇",
      "pffmtz_2425": "//game.gtimg.cn/images/yxzj/zlkdatasys/images/image/20250116/17369908455694.jpg",
      "pffmic_4237": "//game.gtimg.cn/images/yxzj/zlkdatasys/images/image/20250116/17369908474910.jpg"
    }
  ]
}